async_bakalari_api/__init__.py
async_bakalari_api/__main__.py
async_bakalari_api/api_client.py
async_bakalari_api/bakalari.py
async_bakalari_api/bakalari_demo.py
async_bakalari_api/const.py
async_bakalari_api/datastructure.py
async_bakalari_api/exceptions.py
async_bakalari_api/first_login.py
async_bakalari_api/komens.py
async_bakalari_api/logger_api.py
async_bakalari_api/marks.py
async_bakalari_api/timetable.py
async_bakalari_api-0.10.0.dist-info/licenses/LICENSE.md
async_bakalari_api-0.10.0.dist-info/METADATA
async_bakalari_api-0.10.0.dist-info/WHEEL
async_bakalari_api-0.10.0.dist-info/entry_points.txt
async_bakalari_api-0.10.0.dist-info/top_level.txt
async_bakalari_api-0.10.0.dist-info/RECORD
