Metadata-Version: 2.4
Name: async_bakalari_api
Version: 0.10.0
Summary: Async API for Bakalari endpoint v3
Author-email: "Lukas Svoboda (@schizza)" <opensource@schizza.cz>
Maintainer-email: Lukas Svoboda <opensource@schizza.cz>
License: 
Project-URL: Homepage, https://github.com/schizza/bakalari-api3
Project-URL: Documentation, https://async-bakalari-api.schizza.cz
Project-URL: Repository, https://github.com/schizza/bakalari-api3
Project-URL: Bug Tracker, https://github.com/schizza/bakalari-api3/issues
Project-URL: Changelog, https://github.com/schizza/bakalari-api3/blob/master/CHANGELOG.md
Keywords: bakalari,async
Platform: any
Classifier: Development Status :: 4 - Beta
Classifier: Programming Language :: Python
Requires-Python: >=3.13
License-File: LICENSE.md
Requires-Dist: aiofiles>=24.1.0
Requires-Dist: aiohttp>=3.9.5
Requires-Dist: logger>=1.4
Requires-Dist: orjson>=3.10.15
Requires-Dist: python-dateutil>=2.9.0.post0
Requires-Dist: strenum>=0.4.15
Dynamic: license-file
